{
  "title": "Change H key",
  "rules": [
    {
      "description": "Map Hyper + H to left arrow",
      "manipulators": [
        {
          "type": "basic",
          "from": {
            "modifiers": {
              "mandatory": [
                "left_control",
		"left_option",
		"left_command",
		"left_shift"
              ],
              "optional": [
                "caps_lock"
              ]
            },
            "key_code": "h"
          },
          "to": [
            {
              "key_code": "left_arrow"
            }
          ]
        }
      ]
    },
    {
      "description": "Map Control + H to left arrow",
      "manipulators": [
        {
          "type": "basic",
          "from": {
            "modifiers": {
              "mandatory": [
                "left_control"
              ],
              "optional": [
                "caps_lock"
              ]
            },
            "key_code": "h"
          },
          "to": [
            {
              "key_code": "left_arrow"
            }
          ]
        }
      ]
    }
  ]
}
